odoo/addons/sale_stock_reference_by_line/README.rst
odoo/addons/sale_stock_reference_by_line/__init__.py
odoo/addons/sale_stock_reference_by_line/__manifest__.py
odoo/addons/sale_stock_reference_by_line/i18n/ca.po
odoo/addons/sale_stock_reference_by_line/i18n/de.po
odoo/addons/sale_stock_reference_by_line/i18n/el_GR.po
odoo/addons/sale_stock_reference_by_line/i18n/es.po
odoo/addons/sale_stock_reference_by_line/i18n/es_ES.po
odoo/addons/sale_stock_reference_by_line/i18n/es_VE.po
odoo/addons/sale_stock_reference_by_line/i18n/fi.po
odoo/addons/sale_stock_reference_by_line/i18n/fr.po
odoo/addons/sale_stock_reference_by_line/i18n/hr.po
odoo/addons/sale_stock_reference_by_line/i18n/hr_HR.po
odoo/addons/sale_stock_reference_by_line/i18n/hu.po
odoo/addons/sale_stock_reference_by_line/i18n/it.po
odoo/addons/sale_stock_reference_by_line/i18n/nl.po
odoo/addons/sale_stock_reference_by_line/i18n/nl_NL.po
odoo/addons/sale_stock_reference_by_line/i18n/pt.po
odoo/addons/sale_stock_reference_by_line/i18n/pt_BR.po
odoo/addons/sale_stock_reference_by_line/i18n/ro.po
odoo/addons/sale_stock_reference_by_line/i18n/sale_stock_reference_by_line.pot
odoo/addons/sale_stock_reference_by_line/i18n/sk.po
odoo/addons/sale_stock_reference_by_line/i18n/sl.po
odoo/addons/sale_stock_reference_by_line/i18n/tr.po
odoo/addons/sale_stock_reference_by_line/i18n/tr_TR.po
odoo/addons/sale_stock_reference_by_line/i18n/vi_VN.po
odoo/addons/sale_stock_reference_by_line/i18n/zh_CN.po
odoo/addons/sale_stock_reference_by_line/model/__init__.py
odoo/addons/sale_stock_reference_by_line/model/sale.py
odoo/addons/sale_stock_reference_by_line/model/stock_move.py
odoo/addons/sale_stock_reference_by_line/readme/CONTRIBUTORS.md
odoo/addons/sale_stock_reference_by_line/readme/CREDITS.md
odoo/addons/sale_stock_reference_by_line/readme/DESCRIPTION.md
odoo/addons/sale_stock_reference_by_line/static/description/icon.png
odoo/addons/sale_stock_reference_by_line/static/description/index.html
odoo_addon_sale_stock_reference_by_line-19.0.1.0.0.3.dist-info/METADATA
odoo_addon_sale_stock_reference_by_line-19.0.1.0.0.3.dist-info/WHEEL
odoo_addon_sale_stock_reference_by_line-19.0.1.0.0.3.dist-info/top_level.txt
odoo_addon_sale_stock_reference_by_line-19.0.1.0.0.3.dist-info/RECORD
