Metadata-Version: 2.1
Name: odoo-addon-sale_stock_reference_by_line
Version: 19.0.1.0.0.3
Requires-Dist: odoo==19.0.*
Summary: Base module for definition of stock references creation rules for Sale order
Home-page: https://github.com/OCA/sale-workflow
License: AGPL-3
Author: Camptocamp,ForgeFlow,Serpent Consulting Services Pvt. Ltd.,Odoo Community Association (OCA), SprintIT Ltd.
Author-email: support@odoo-community.org
Classifier: Programming Language :: Python
Classifier: Framework :: Odoo
Classifier: Framework :: Odoo :: 19.0
Classifier: License :: OSI Approved :: GNU Affero General Public License v3
Classifier: Development Status :: 5 - Production/Stable
